disnake/ext/components/__init__.py
disnake/ext/components/py.typed
disnake_ext_components-0.0.0a0.dist-info/LICENSE
disnake_ext_components-0.0.0a0.dist-info/METADATA
disnake_ext_components-0.0.0a0.dist-info/WHEEL
disnake_ext_components-0.0.0a0.dist-info/top_level.txt
disnake_ext_components-0.0.0a0.dist-info/RECORD
