Metadata-Version: 2.1
Name: disnake-ext-components
Version: 0.0.0a0
Summary: A component listener wrapper for disnake
Home-page: https://github.com/DisnakeCommunity/disnake-ext-components
Author: Disnake Community
License: MIT
Classifier: Development Status :: 4 - Beta
Classifier: License :: OSI Approved :: MIT License
Classifier: Intended Audience :: Developers
Classifier: Natural Language :: English
Classifier: Operating System :: OS Independent
Classifier: Programming Language :: Python :: 3.8
Classifier: Programming Language :: Python :: 3.9
Classifier: Programming Language :: Python :: 3.10
Classifier: Topic :: Internet
Classifier: Topic :: Software Development :: Libraries
Classifier: Topic :: Software Development :: Libraries :: Python Modules
Classifier: Topic :: Utilities
Classifier: Typing :: Typed
Requires-Python: >=3.8.0
License-File: LICENSE
Requires-Dist: disnake (>=2.5.0)
Requires-Dist: typing-extensions
